breezeml/__init__.py
breezeml/breezeml.py
breezeml/classifiers.py
breezeml/clustering.py
breezeml-0.1.2.dist-info/licenses/LICENSE
breezeml-0.1.2.dist-info/METADATA
breezeml-0.1.2.dist-info/WHEEL
breezeml-0.1.2.dist-info/top_level.txt
breezeml-0.1.2.dist-info/RECORD
