Metadata-Version: 2.4
Name: breezeml
Version: 0.1.2
Summary: 🌬️ BreezeML 🔥✨ — A beginner-friendly machine learning library built on scikit-learn.
Author-email: Akash Anipakalu Giridhar <akash@example.com>
License: MIT
Project-URL: Homepage, https://github.com/venomez-viper/breezeml
Project-URL: Repository, https://github.com/venomez-viper/breezeml
Project-URL: Issues, https://github.com/venomez-viper/breezeml/issues
Project-URL: Documentation, https://pypi.org/project/breezeml/
Keywords: machine learning,education,scikit-learn,beginner
Classifier: Programming Language :: Python :: 3
Classifier: License :: OSI Approved :: MIT License
Classifier: Operating System :: OS Independent
Classifier: Topic :: Scientific/Engineering :: Artificial Intelligence
Classifier: Intended Audience :: Education
Requires-Python: >=3.8
License-File: LICENSE
Requires-Dist: pandas
Requires-Dist: numpy
Requires-Dist: scikit-learn
Requires-Dist: joblib
Dynamic: license-file
